odoo9_addon_auth_keycloak-9.0.1.0.0.99.dev10-py3.8-nspkg.pth
odoo_addons/auth_keycloak/README.rst
odoo_addons/auth_keycloak/__init__.py
odoo_addons/auth_keycloak/__openerp__.py
odoo_addons/auth_keycloak/exceptions.py
odoo_addons/auth_keycloak/data/auth_oauth_provider.xml
odoo_addons/auth_keycloak/examples/README.md
odoo_addons/auth_keycloak/examples/__init__.py
odoo_addons/auth_keycloak/examples/cli.py
odoo_addons/auth_keycloak/examples/common.py
odoo_addons/auth_keycloak/examples/get_token.py
odoo_addons/auth_keycloak/examples/keycloak-compose.yml
odoo_addons/auth_keycloak/examples/odoo-client.json
odoo_addons/auth_keycloak/examples/realm-export.json
odoo_addons/auth_keycloak/examples/requirements.txt
odoo_addons/auth_keycloak/i18n/auth_keycloak.pot
odoo_addons/auth_keycloak/i18n/fr.po
odoo_addons/auth_keycloak/models/__init__.py
odoo_addons/auth_keycloak/models/auth_oauth.py
odoo_addons/auth_keycloak/models/res_users.py
odoo_addons/auth_keycloak/readme/CONFIGURE.rst
odoo_addons/auth_keycloak/readme/CONTRIBUTORS.rst
odoo_addons/auth_keycloak/readme/CREDITS.rst
odoo_addons/auth_keycloak/readme/DESCRIPTION.rst
odoo_addons/auth_keycloak/readme/HISTORY.rst
odoo_addons/auth_keycloak/readme/USAGE.rst
odoo_addons/auth_keycloak/static/description/icon.png
odoo_addons/auth_keycloak/static/description/index.html
odoo_addons/auth_keycloak/tests/__init__.py
odoo_addons/auth_keycloak/tests/common.py
odoo_addons/auth_keycloak/tests/test_auth.py
odoo_addons/auth_keycloak/tests/test_wizard_create.py
odoo_addons/auth_keycloak/tests/test_wizard_sync.py
odoo_addons/auth_keycloak/views/auth_oauth_views.xml
odoo_addons/auth_keycloak/views/res_users_views.xml
odoo_addons/auth_keycloak/wizard/__init__.py
odoo_addons/auth_keycloak/wizard/keycloak_create_wiz.xml
odoo_addons/auth_keycloak/wizard/keycloak_sync_wiz.py
odoo_addons/auth_keycloak/wizard/keycloak_sync_wiz.xml
odoo9_addon_auth_keycloak-9.0.1.0.0.99.dev10.dist-info/METADATA
odoo9_addon_auth_keycloak-9.0.1.0.0.99.dev10.dist-info/WHEEL
odoo9_addon_auth_keycloak-9.0.1.0.0.99.dev10.dist-info/namespace_packages.txt
odoo9_addon_auth_keycloak-9.0.1.0.0.99.dev10.dist-info/top_level.txt
odoo9_addon_auth_keycloak-9.0.1.0.0.99.dev10.dist-info/RECORD
